{
    "date": "2026-04-08",
    "dbgA2Upom4Rj7lZOlRlL": {
        "high_water_mark": 0.0,
        "armed": false,
        "name": "Copy of Feaver Dream UBR RSI",
        "account": "88509a93-d466-46bd-8833-73db57322798",
        "current_return": 0.0,
        "mc_prob": 46.9
    },
    "cuOYd9prYIx8xLfiJihs": {
        "high_water_mark": 0.0,
        "armed": false,
        "name": "Copy of Script Kiddie Feaver Dream UBR RSI",
        "account": "88509a93-d466-46bd-8833-73db57322798",
        "current_return": 0.0,
        "mc_prob": 47.32
    },
    "HV47VktMSDvqj8OgqaKE": {
        "high_water_mark": 0.0,
        "armed": false,
        "name": "Copy of HODL mFR|KMLM",
        "account": "88509a93-d466-46bd-8833-73db57322798",
        "current_return": 0.0,
        "mc_prob": 46.94
    },
    "J4T6SxPk8vL875EhDdIw": {
        "high_water_mark": 0.0,
        "armed": false,
        "name": "Copy of HODL FR",
        "account": "88509a93-d466-46bd-8833-73db57322798",
        "current_return": 0.0,
        "mc_prob": 59.68
    },
    "NfQwQoy6WJPT8G22hE5Z": {
        "high_water_mark": 0.0,
        "armed": false,
        "name": "Copy of Chocolatey Mini Benetton | 80% | Calmar",
        "account": "88509a93-d466-46bd-8833-73db57322798",
        "current_return": 0.0,
        "mc_prob": 54.6
    },
    "7nV4dqdbm6yPHDjayJK1": {
        "high_water_mark": 0.0,
        "armed": false,
        "name": "Copy of 50d RSI LQD > XLV Risk On/Off",
        "account": "88509a93-d466-46bd-8833-73db57322798",
        "current_return": 0.0,
        "mc_prob": 62.46000000000001
    },
    "LBgdp0ti8rLGHhfRS8zQ": {
        "high_water_mark": 0.0,
        "armed": false,
        "name": "Copy of Anansi Portfolio | Simplified LBT",
        "account": "88509a93-d466-46bd-8833-73db57322798",
        "current_return": 0.0,
        "mc_prob": 60.9
    },
    "v289CsEcVcOohPYGruxD": {
        "high_water_mark": 0.0,
        "armed": false,
        "name": "Copy of TWF FW (TWF Base v26) vAll-01 + FR v1",
        "account": "88509a93-d466-46bd-8833-73db57322798",
        "current_return": 0.0,
        "mc_prob": 61.040000000000006
    },
    "9zfiCHNWY7Y7u5il0xvS": {
        "high_water_mark": 0.0,
        "armed": false,
        "name": "Copy of HODL Chicken & Fried Rice | De-Debased Simplified Portfolio | Mini Benetton | 80% | Calmar | Jope IRA",
        "account": "88509a93-d466-46bd-8833-73db57322798",
        "current_return": 0.0,
        "mc_prob": 57.98
    },
    "ybo0XGR3LD2yYCFwbbBu": {
        "high_water_mark": 0.0,
        "armed": false,
        "name": "Copy of 15 FR + KozBonds",
        "account": "88509a93-d466-46bd-8833-73db57322798",
        "current_return": 0.0,
        "mc_prob": 65.72
    },
    "Tiza8lqyivzM0jUvtYCC": {
        "high_water_mark": 0.0,
        "armed": false,
        "name": "Copy of MbM | Hedged FTLT",
        "account": "88509a93-d466-46bd-8833-73db57322798",
        "current_return": 0.0,
        "mc_prob": 55.2
    },
    "Q3JEov68kpRegz8crQaK": {
        "high_water_mark": 0.0,
        "armed": false,
        "name": "Copy of FOUR SQUARES | Mini Benetton | 80% | Calmar | Jope IRA",
        "account": "88509a93-d466-46bd-8833-73db57322798",
        "current_return": 0.0,
        "mc_prob": 51.160000000000004
    },
    "fjv63lbiorEhLRAPFEFN": {
        "high_water_mark": 0.0,
        "armed": false,
        "name": "Copy of MOST AR NO MATTER WHAT STFU SIT DOWN AND HOLD ON v1.1 | Mini Benetton | 80% | Calmar | Jope IRA",
        "account": "88509a93-d466-46bd-8833-73db57322798",
        "current_return": 0.0,
        "mc_prob": 41.9
    },
    "pHzwuCy1MSyOBBnhPNJc": {
        "high_water_mark": 0.0,
        "armed": false,
        "name": "Copy of v3 The Absolute Lowest Vol High AR | Mini Benetton | 80% | Calmar | Jope IRA",
        "account": "88509a93-d466-46bd-8833-73db57322798",
        "current_return": 0.0,
        "mc_prob": 61.0
    },
    "jh0JhJhXZ45cDR7zBi0U": {
        "high_water_mark": 0.0,
        "armed": false,
        "name": "Copy of AutoRunners | SMABoxes | 3x",
        "account": "88509a93-d466-46bd-8833-73db57322798",
        "current_return": 0.0,
        "mc_prob": 49.34
    },
    "vr2vqxoiBStU4GAtLP9n": {
        "high_water_mark": 0.0,
        "armed": false,
        "name": "Copy of AutoRunners | EM ONLY",
        "account": "88509a93-d466-46bd-8833-73db57322798",
        "current_return": 0.0,
        "mc_prob": 48.82
    },
    "vgwBmKXtJcCKlxlZcXCy": {
        "high_water_mark": 0.0,
        "armed": false,
        "name": "Copy of Moon Mission v3 | Mini Benetton | 80% | Calmar | Jope IRA",
        "account": "88509a93-d466-46bd-8833-73db57322798",
        "current_return": 0.0,
        "mc_prob": 41.8
    },
    "jqDW57tdzXeB8tTd5pDV": {
        "high_water_mark": 0.0,
        "armed": false,
        "name": "Copy of Long/Short Mini Benetton | 80% | Calmar | Jope IRA",
        "account": "88509a93-d466-46bd-8833-73db57322798",
        "current_return": 0.0,
        "mc_prob": 63.959999999999994
    },
    "Optn1VcTcPdUzLzrN5kS": {
        "high_water_mark": 0.0,
        "armed": false,
        "name": "Copy of AutoRunners | Markets? EMERGED + OOS AutoTuned + Slim Jim (Crypto Juice+) | NOVA",
        "account": "88509a93-d466-46bd-8833-73db57322798",
        "current_return": 0.0,
        "mc_prob": 48.28
    },
    "NWcLcv9m09dynGMl1Jfg": {
        "high_water_mark": 0.0,
        "armed": false,
        "name": "Copy of LIQ. WHS: AutoRunners | OOS AutoTuned (Invest Copy) | LIVE 1.2.25-4.1.25 -11%",
        "account": "88509a93-d466-46bd-8833-73db57322798",
        "current_return": 0.0,
        "mc_prob": 53.04
    },
    "KDjtKDjlQJ0IiSO3DyfQ": {
        "high_water_mark": 0.0,
        "armed": false,
        "name": "Copy of And I Ran, I Ran to Anansi ",
        "account": "88509a93-d466-46bd-8833-73db57322798",
        "current_return": 0.0,
        "mc_prob": 54.2
    },
    "Xk6WiKfA7IK8Axg4SMxr": {
        "high_water_mark": 0.0,
        "armed": false,
        "name": "Copy of Nova Feaver FR | 2/3 Core | Jope IRA",
        "account": "88509a93-d466-46bd-8833-73db57322798",
        "current_return": 0.0,
        "mc_prob": 58.8
    },
    "CkNiTbykxq13XdwYUx7M": {
        "high_water_mark": 0.0,
        "armed": false,
        "name": "Copy of Autotune OPTIMIZED Mix 2 Mini Benetton | 80% | Calmar | Jope IRA",
        "account": "88509a93-d466-46bd-8833-73db57322798",
        "current_return": 0.0,
        "mc_prob": 56.879999999999995
    },
    "uaPwKFUmVVIUyWAUgyhO": {
        "high_water_mark": 0.0,
        "armed": false,
        "name": "Copy of 81-89 FR December 2025 | Jope IRA",
        "account": "88509a93-d466-46bd-8833-73db57322798",
        "current_return": 0.0,
        "mc_prob": 61.339999999999996
    },
    "gHMMARhXBLwFMLgIUY7E": {
        "high_water_mark": 0.0,
        "armed": false,
        "name": "Copy of Koz | Anansi Collection",
        "account": "88509a93-d466-46bd-8833-73db57322798",
        "current_return": 0.0,
        "mc_prob": 56.56
    },
    "5L5hSveRouvJLvjNbhkK": {
        "high_water_mark": 0.0,
        "armed": false,
        "name": "Copy of Mini AutoRunners VibeCheck or Chocolate Milk OPT | Mini Benetton | 80% | Calmar | Jope IRA",
        "account": "88509a93-d466-46bd-8833-73db57322798",
        "current_return": 0.0,
        "mc_prob": 28.860000000000003
    },
    "tpMeXMSJ59mowtEGZqeC": {
        "high_water_mark": 0.0,
        "armed": false,
        "name": "Copy of Feaver Dreams and NOVA | UVXY | Jope IRA",
        "account": "88509a93-d466-46bd-8833-73db57322798",
        "current_return": 0.0,
        "mc_prob": 56.32
    },
    "q4VE9qdhiiSa49ynM3EP": {
        "high_water_mark": 0.0,
        "armed": false,
        "name": "Copy of Dan's Semi/Memory/Optics/Comms/Power + Korean 4TLT | okhi2u | Mini Benetton | 80% | Calmar | Jope IRA",
        "account": "88509a93-d466-46bd-8833-73db57322798",
        "current_return": 0.0,
        "mc_prob": 59.019999999999996
    },
    "oszUCt2SDzxVWgZZ7Nso": {
        "high_water_mark": 0.0,
        "armed": false,
        "name": "Copy of Anansi Mixed Signals",
        "account": "88509a93-d466-46bd-8833-73db57322798",
        "current_return": 0.0,
        "mc_prob": 58.4
    },
    "a5SAPRvAyoweLb7D3IUb": {
        "high_water_mark": 0.0,
        "armed": false,
        "name": "Copy of MbM | Always Hedged Timeframe Trends v0.0.0.1 ",
        "account": "88509a93-d466-46bd-8833-73db57322798",
        "current_return": 0.0,
        "mc_prob": 47.32
    },
    "0Id7TuELUDe8rp1goCB5": {
        "high_water_mark": 0.0,
        "armed": false,
        "name": "Copy of AutoRunners | Just The FrontRunners | Optimized",
        "account": "88509a93-d466-46bd-8833-73db57322798",
        "current_return": 0.0,
        "mc_prob": 90.03999999999999
    },
    "K5bWyyyYnKBhDlMYDwCK": {
        "high_water_mark": 0.0,
        "armed": false,
        "name": "Copy of TWF STFU and Chill More",
        "account": "88509a93-d466-46bd-8833-73db57322798",
        "current_return": 0.0,
        "mc_prob": 64.46
    },
    "zUqtEPtXftjL2e146CZT": {
        "high_water_mark": 0.0,
        "armed": false,
        "name": "Copy of Champagne & Cocaine Optimized",
        "account": "88509a93-d466-46bd-8833-73db57322798",
        "current_return": 0.0,
        "mc_prob": 45.76
    },
    "T9YAC2GtXl4zZYq7Pixn": {
        "high_water_mark": 0.0,
        "armed": false,
        "name": "Copy of AutoRunners | United Colors of Benetton | non-MINI",
        "account": "88509a93-d466-46bd-8833-73db57322798",
        "current_return": 0.0,
        "mc_prob": 49.54
    },
    "zyVgsAWto7drqKVj9EhT": {
        "high_water_mark": 0.0,
        "armed": false,
        "name": "Copy of US Equities | Multi-Runner | 2025-10-20",
        "account": "88509a93-d466-46bd-8833-73db57322798",
        "current_return": 0.0,
        "mc_prob": 53.7
    },
    "TGso99kWiVnMtyXAuPd9": {
        "high_water_mark": 0.0,
        "armed": false,
        "name": "Copy of Go for Gold | Simplified",
        "account": "88509a93-d466-46bd-8833-73db57322798",
        "current_return": 0.0,
        "mc_prob": 58.699999999999996
    },
    "HGlMykscgFIiAIfKs7vx": {
        "high_water_mark": 0.0,
        "armed": false,
        "name": "Copy of Walter | Anansi Collection",
        "account": "88509a93-d466-46bd-8833-73db57322798",
        "current_return": 0.0,
        "mc_prob": 47.12
    },
    "IuyI9QfH8gDqJxCMS6mR": {
        "high_water_mark": 0.0,
        "armed": false,
        "name": "Copy of Long/Short (SPY/VIXM+SVXY) | UVXY Scale In",
        "account": "88509a93-d466-46bd-8833-73db57322798",
        "current_return": 0.0,
        "mc_prob": 71.41999999999999
    },
    "zyPInj4kyZItMLKHRBFB": {
        "high_water_mark": 0.0,
        "armed": false,
        "name": "Copy of v2 USD Nested SOXL Autotuned w/ a FEAVER | Mini Benetton | 80% | Calmar | Jope IRA",
        "account": "88509a93-d466-46bd-8833-73db57322798",
        "current_return": 0.0,
        "mc_prob": 51.4
    },
    "gFkA8kS7z8gt16CYKIMG": {
        "high_water_mark": 0.0,
        "armed": false,
        "name": "Copy of TWF FW (Base v2) vAll-01 + FR v1",
        "account": "88509a93-d466-46bd-8833-73db57322798",
        "current_return": 0.0,
        "mc_prob": 53.68000000000001
    },
    "4llQHcL3Ajbpbe8GoCUo": {
        "high_water_mark": 0.0,
        "armed": false,
        "name": "Copy of WHSMacon : Vengeance Sync R\u0394 -Hyper Drive- Edition ",
        "account": "88509a93-d466-46bd-8833-73db57322798",
        "current_return": 0.0,
        "mc_prob": 46.68
    },
    "EXV4uUfeNJybrXc1Hhc7": {
        "high_water_mark": 0.0,
        "armed": false,
        "name": "Copy of TWF STFU, HODL, and Chill | Jope IRA",
        "account": "88509a93-d466-46bd-8833-73db57322798",
        "current_return": 0.0,
        "mc_prob": 62.06
    },
    "ZpvRdS0YlFVDOEMYfuZ0": {
        "high_water_mark": 0.0,
        "armed": false,
        "name": "Copy of Autotune OPTIMIZED | AutoRunners United Colors of Benetton HOLD | Mini Benetton | 80% | Calmar | Jope IRA",
        "account": "88509a93-d466-46bd-8833-73db57322798",
        "current_return": 0.0,
        "mc_prob": 53.6
    },
    "dZqnuX6ngTo3yT9oK0YU": {
        "high_water_mark": 0.0,
        "armed": false,
        "name": "Copy of Nova Feaver | Mini Benetton | 80% | Calmar | Jope IRA",
        "account": "88509a93-d466-46bd-8833-73db57322798",
        "current_return": 0.0,
        "mc_prob": 53.72
    },
    "xA13leXZcrDy2mlSp5JB": {
        "high_water_mark": 0.0,
        "armed": false,
        "name": "Copy of 30y OS TQQQ | Nova Feaver 2/3 Core | Mini Benetton | 80% | Calmar | Jope IRA",
        "account": "88509a93-d466-46bd-8833-73db57322798",
        "current_return": 0.0,
        "mc_prob": 53.779999999999994
    },
    "JnWloxkDzpDnG2BoPD5N": {
        "high_water_mark": 0.0,
        "armed": false,
        "name": "Copy of UltraAutoRunners | KMLM/1968/HOLD",
        "account": "88509a93-d466-46bd-8833-73db57322798",
        "current_return": 0.0,
        "mc_prob": 52.580000000000005
    },
    "Gf1NriqFgjWB8j5K7X4q": {
        "high_water_mark": 0.0,
        "armed": false,
        "name": "Copy of Golden Ratio Portfolio v20260210 (Zaied + Gold Nova Feaver + GOLD / UGL mixer + Nova Feaver) | Jope IRA",
        "account": "88509a93-d466-46bd-8833-73db57322798",
        "current_return": 0.0,
        "mc_prob": 57.82000000000001
    },
    "kkRCo8F4a0iqzoOrCy5B": {
        "high_water_mark": 0.0,
        "armed": false,
        "name": "Copy of UltraRunner | Static Hold",
        "account": "88509a93-d466-46bd-8833-73db57322798",
        "current_return": 0.0,
        "mc_prob": 54.0
    },
    "2hXGy0FMz9hveWMZag45": {
        "high_water_mark": 0.0,
        "armed": false,
        "name": "Copy of FSTRAT 29a5 FRUNNER 17 + UCOB + NOVA V1.21c.3a1 HEDGE | OPTIMIZED CAGR Sortino",
        "account": "88509a93-d466-46bd-8833-73db57322798",
        "current_return": 0.0,
        "mc_prob": 61.68
    },
    "SnZ5zCFsDy6xhAFlxkDP": {
        "high_water_mark": 0.0,
        "armed": false,
        "name": "Copy of Corp > Sectors | 2025-11-17",
        "account": "88509a93-d466-46bd-8833-73db57322798",
        "current_return": 0.0,
        "mc_prob": 54.279999999999994
    },
    "GqTfCYpYo240z2NNEiN3": {
        "high_water_mark": 0.0,
        "armed": false,
        "name": "Copy of 30y OS TQQQ | Mini AutoRunners VibeCheck or Chocolate Milk OPT | Mini Benetton | 80% | Calmar | Jope IRA",
        "account": "88509a93-d466-46bd-8833-73db57322798",
        "current_return": 0.0,
        "mc_prob": 59.68
    },
    "HiXOd6qemhhiDchuiyKB": {
        "high_water_mark": 0.0,
        "armed": false,
        "name": "Copy of Jason likes stuff remix",
        "account": "88509a93-d466-46bd-8833-73db57322798",
        "current_return": 0.0,
        "mc_prob": 49.9
    },
    "jTtsAmKRhuR5mnzpU6Y1": {
        "high_water_mark": 0.0,
        "armed": false,
        "name": "Copy of AutoRunners | SPY 200d",
        "account": "88509a93-d466-46bd-8833-73db57322798",
        "current_return": 0.0,
        "mc_prob": 53.2
    },
    "RDLIHxEtBQJvVwALZspf": {
        "high_water_mark": 0.0,
        "armed": false,
        "name": "Copy of AutoRunners | Conjoined Triangles of Success",
        "account": "88509a93-d466-46bd-8833-73db57322798",
        "current_return": 0.0,
        "mc_prob": 45.379999999999995
    },
    "zDhwGIOqYleO9y1nBJyu": {
        "high_water_mark": 0.0,
        "armed": false,
        "name": "Copy of Mini Benetton | 80% | Calmar",
        "account": "88509a93-d466-46bd-8833-73db57322798",
        "current_return": 0.0,
        "mc_prob": 48.54
    },
    "Xqz9K3QID5QxrFjgeSBW": {
        "high_water_mark": 0.0,
        "armed": false,
        "name": "Copy of SHNY FTLT | Mini Benetton | 80% | Calmar | Jope IRA",
        "account": "88509a93-d466-46bd-8833-73db57322798",
        "current_return": 0.0,
        "mc_prob": 56.68
    },
    "JT2j1CCdoQKTyur4ikvy": {
        "high_water_mark": 0.0,
        "armed": false,
        "name": "Copy of TESTPORT #018.2: Sector Rotator",
        "account": "88509a93-d466-46bd-8833-73db57322798",
        "current_return": 0.0,
        "mc_prob": 55.86
    },
    "nESDK35u8J6vlZYY9TIm": {
        "high_water_mark": 0.0,
        "armed": false,
        "name": "Copy of Designed FR | Testfolio",
        "account": "88509a93-d466-46bd-8833-73db57322798",
        "current_return": 0.0,
        "mc_prob": 72.36
    },
    "69BNETx68SRLy1nsRlzo": {
        "high_water_mark": 0.0,
        "armed": false,
        "name": "Copy of UltraRunner Optimized",
        "account": "88509a93-d466-46bd-8833-73db57322798",
        "current_return": 0.0,
        "mc_prob": 71.14
    },
    "WEDa49hf9scForxAWp4g": {
        "high_water_mark": 0.0,
        "armed": false,
        "name": "Copy of I like stuff on sale",
        "account": "88509a93-d466-46bd-8833-73db57322798",
        "current_return": 0.0,
        "mc_prob": 55.82
    },
    "04yxysRv8eJ4oqnwRo21": {
        "high_water_mark": 0.0,
        "armed": false,
        "name": "Copy of DIA/FXI/QQQ FR | Europe, Gold, USA mashup | okhi2u | Jope IRA",
        "account": "88509a93-d466-46bd-8833-73db57322798",
        "current_return": 0.0,
        "mc_prob": 57.16
    },
    "nC07hmAVmc673e4CNe3B": {
        "high_water_mark": 0.0,
        "armed": false,
        "name": "Copy of US Equities Multi-Runner | DIA/FXI/QQQ FR | 2025-10-20 (VIXY -> UVIX) | Jope IRA",
        "account": "88509a93-d466-46bd-8833-73db57322798",
        "current_return": 0.0,
        "mc_prob": 52.86
    },
    "W22pXmrnSJHWWJsCjGJd": {
        "high_water_mark": 0.0,
        "armed": false,
        "name": "Copy of QQQ 1996 MA | Feaver Dream\u2122 | Jope IRA",
        "account": "88509a93-d466-46bd-8833-73db57322798",
        "current_return": 0.0,
        "mc_prob": 60.86
    },
    "G4z9lY9zjqJ5JkDk8UT0": {
        "high_water_mark": 0.0,
        "armed": false,
        "name": "Copy of QQQ 1996 KMLM | Feaver Dream\u2122 | Jope IRA",
        "account": "88509a93-d466-46bd-8833-73db57322798",
        "current_return": 0.0,
        "mc_prob": 61.31999999999999
    },
    "NBaWVg2Lkg7ZNB55Wmtj": {
        "high_water_mark": 0.0,
        "armed": false,
        "name": "Copy of EET | Exxahub",
        "account": "88509a93-d466-46bd-8833-73db57322798",
        "current_return": 0.0,
        "mc_prob": 89.84
    },
    "A8mpV3HjVIvIMaJYIngW": {
        "high_water_mark": 0.0,
        "armed": false,
        "name": "Copy of 80% | Calmar",
        "account": "88509a93-d466-46bd-8833-73db57322798",
        "current_return": 0.0,
        "mc_prob": 89.56
    },
    "neYLFz9ixZmqufguTBjG": {
        "high_water_mark": 0.0,
        "armed": false,
        "name": "Copy of 79 FR",
        "account": "88509a93-d466-46bd-8833-73db57322798",
        "current_return": 0.0,
        "mc_prob": 89.66
    },
    "cPaq6gQIubQLvxTme82O": {
        "high_water_mark": 0.0,
        "armed": false,
        "name": "Copy of AutoRunner | 80% | AR + Calmar",
        "account": "88509a93-d466-46bd-8833-73db57322798",
        "current_return": 0.0,
        "mc_prob": 89.12
    },
    "2BsBC7oxL0FUoFhNCYXP": {
        "high_water_mark": 0.0,
        "armed": false,
        "name": "Copy of AutoRunners | Just The FrontRunners | 80% | Calmar",
        "account": "88509a93-d466-46bd-8833-73db57322798",
        "current_return": 0.0,
        "mc_prob": 90.82000000000001
    },
    "3kPvhkNM8lE3mJyfiVf1": {
        "high_water_mark": 0.0,
        "armed": false,
        "name": "Copy of VIXRunner Mashup",
        "account": "88509a93-d466-46bd-8833-73db57322798",
        "current_return": 0.0,
        "mc_prob": 90.12
    },
    "kg0vyf5CDT7YjSvI8mmm": {
        "high_water_mark": 0.0,
        "armed": false,
        "name": "Copy of DIA 1998 KMLM | Feaver Dream\u2122 | Jope IRA",
        "account": "88509a93-d466-46bd-8833-73db57322798",
        "current_return": 0.0,
        "mc_prob": 52.88
    },
    "9GKuz8zaCtbaBEeRIzWq": {
        "high_water_mark": 0.0,
        "armed": false,
        "name": "Copy of DIA 1998 MA | Feaver Dream\u2122 | Jope IRA",
        "account": "88509a93-d466-46bd-8833-73db57322798",
        "current_return": 0.0,
        "mc_prob": 51.85999999999999
    },
    "rgCqStOj0WK9fJcYynQw": {
        "high_water_mark": 0.0,
        "armed": false,
        "name": "Copy of Long/Short Mini Benetton | 80% | Calmar | Jope IRA",
        "account": "585b26c6-62bf-4a48-ab01-5ff8acb66f99",
        "current_return": 0.0,
        "mc_prob": 64.53999999999999
    },
    "cU4Tort49N6o5G0JAHDw": {
        "high_water_mark": 0.0,
        "armed": false,
        "name": "Copy of 30y OS TQQQ | Nova Feaver 2/3 Core | Mini Benetton | 80% | Calmar | Jope IRA",
        "account": "585b26c6-62bf-4a48-ab01-5ff8acb66f99",
        "current_return": 0.0,
        "mc_prob": 53.879999999999995
    },
    "hlANZF5nD4VvPbNvP0an": {
        "high_water_mark": 0.0,
        "armed": false,
        "name": "Copy of Mini AutoRunners VibeCheck or Chocolate Milk OPT | Mini Benetton | 80% | Calmar | Jope IRA",
        "account": "585b26c6-62bf-4a48-ab01-5ff8acb66f99",
        "current_return": 0.0,
        "mc_prob": 27.700000000000003
    },
    "XxsntueWxpQcBE9tZFS7": {
        "high_water_mark": 0.0,
        "armed": false,
        "name": "Copy of Nova Feaver FR | 2/3 Core | Jope IRA",
        "account": "585b26c6-62bf-4a48-ab01-5ff8acb66f99",
        "current_return": 0.0,
        "mc_prob": 59.760000000000005
    },
    "i9gd767MGrAcvXLjGB8Z": {
        "high_water_mark": 0.0,
        "armed": false,
        "name": "Copy of DIA 1998 KMLM | Feaver Dream\u2122 | Jope IRA",
        "account": "585b26c6-62bf-4a48-ab01-5ff8acb66f99",
        "current_return": 0.0,
        "mc_prob": 53.459999999999994
    },
    "yZq3gUwieUYbVInnmbjU": {
        "high_water_mark": 0.0,
        "armed": false,
        "name": "Copy of HODL Chicken & Fried Rice | De-Debased Simplified Portfolio | Mini Benetton | 80% | Calmar | Jope IRA",
        "account": "585b26c6-62bf-4a48-ab01-5ff8acb66f99",
        "current_return": 0.0,
        "mc_prob": 59.48
    },
    "vJfbWMA4mKTiH7jEMjcd": {
        "high_water_mark": 0.0,
        "armed": false,
        "name": "Copy of Nova Feaver | Mini Benetton | 80% | Calmar | Jope IRA",
        "account": "585b26c6-62bf-4a48-ab01-5ff8acb66f99",
        "current_return": 0.0,
        "mc_prob": 53.38
    },
    "UbFmbGH9RU83qIOWxGK1": {
        "high_water_mark": 0.0,
        "armed": false,
        "name": "Copy of Moon Mission v3 | Nova Fever FR | Jope IRA",
        "account": "585b26c6-62bf-4a48-ab01-5ff8acb66f99",
        "current_return": 0.0,
        "mc_prob": 42.18
    },
    "i22tAs8OUf05sjrBDBXA": {
        "high_water_mark": 0.0,
        "armed": false,
        "name": "Copy of US Equities Multi-Runner | DIA/FXI/QQQ FR | 2025-10-20 (VIXY -> UVIX) | Jope IRA",
        "account": "585b26c6-62bf-4a48-ab01-5ff8acb66f99",
        "current_return": 0.0,
        "mc_prob": 53.26
    },
    "OVTGXXA5foNupPCMyEIp": {
        "high_water_mark": 0.0,
        "armed": false,
        "name": "Copy of Four square shorting homies | okhi2u | Mini Benetton | 80% | Calmar | Jope IRA",
        "account": "585b26c6-62bf-4a48-ab01-5ff8acb66f99",
        "current_return": 0.0,
        "mc_prob": 54.120000000000005
    },
    "vM6j3hxn4gxTGIcQIoGh": {
        "high_water_mark": 0.0,
        "armed": false,
        "name": "Copy of QQQ 1996 MA | Feaver Dream\u2122 | Jope IRA",
        "account": "585b26c6-62bf-4a48-ab01-5ff8acb66f99",
        "current_return": 0.0,
        "mc_prob": 59.940000000000005
    },
    "t7WAjISsASCLJgoYh3Iq": {
        "high_water_mark": 0.0,
        "armed": false,
        "name": "Copy of QQQ 1996 KMLM | Feaver Dream\u2122 | Jope IRA",
        "account": "585b26c6-62bf-4a48-ab01-5ff8acb66f99",
        "current_return": 0.0,
        "mc_prob": 58.96
    },
    "jDKipwGx6ZchK21PGyGN": {
        "high_water_mark": 0.0,
        "armed": false,
        "name": "Copy of DIA 1998 MA | Feaver Dream\u2122 | Jope IRA",
        "account": "585b26c6-62bf-4a48-ab01-5ff8acb66f99",
        "current_return": 0.0,
        "mc_prob": 52.580000000000005
    },
    "UTHLt0ucCoIf7jMxmz13": {
        "high_water_mark": 0.0,
        "armed": false,
        "name": "Copy of Chocolatey Mini Benetton | 80% | Calmar",
        "account": "585b26c6-62bf-4a48-ab01-5ff8acb66f99",
        "current_return": 0.0,
        "mc_prob": 55.00000000000001
    },
    "4rTerezQ45GjbTpU8DFX": {
        "high_water_mark": 0.0,
        "armed": false,
        "name": "Copy of Golden Ratio Portfolio v20260210 (Zaied + Gold Nova Feaver + GOLD / UGL mixer + Nova Feaver) | Jope IRA",
        "account": "585b26c6-62bf-4a48-ab01-5ff8acb66f99",
        "current_return": 0.0,
        "mc_prob": 57.84
    },
    "veB83UxxxJwInVDHOAPj": {
        "high_water_mark": 0.0,
        "armed": false,
        "name": "Copy of v2 USD Nested SOXL Autotuned w/ a Shorty | Mini Benetton | 80% | Calmar | Jope IRA",
        "account": "585b26c6-62bf-4a48-ab01-5ff8acb66f99",
        "current_return": 0.0,
        "mc_prob": 42.52
    },
    "TI2BtDxcc5giOzJHspWJ": {
        "high_water_mark": 0.0,
        "armed": false,
        "name": "Copy of 30y OS TQQQ | Mini AutoRunners VibeCheck or Chocolate Milk OPT | Mini Benetton | 80% | Calmar | Jope IRA",
        "account": "585b26c6-62bf-4a48-ab01-5ff8acb66f99",
        "current_return": 0.0,
        "mc_prob": 60.699999999999996
    },
    "FZXgyXswue8bDnjJ0iJn": {
        "high_water_mark": 0.0,
        "armed": false,
        "name": "Copy of MOST AR NO MATTER WHAT STFU SIT DOWN AND HOLD ON v1.1 | Mini Benetton | 80% | Calmar | Jope IRA",
        "account": "585b26c6-62bf-4a48-ab01-5ff8acb66f99",
        "current_return": 0.0,
        "mc_prob": 43.34
    },
    "jyNArE4sI8r2IUEZmYyV": {
        "high_water_mark": 0.0,
        "armed": false,
        "name": "Copy of Autotune OPTIMIZED Mix 2 Mini Benetton | 80% | Calmar | Jope IRA",
        "account": "585b26c6-62bf-4a48-ab01-5ff8acb66f99",
        "current_return": 0.0,
        "mc_prob": 58.08
    },
    "2k4aeo6QWpQxUaHRjZFT": {
        "high_water_mark": 0.0,
        "armed": false,
        "name": "Copy of v3 The Absolute Lowest Vol High AR | Mini Benetton | 80% | Calmar | Jope IRA",
        "account": "585b26c6-62bf-4a48-ab01-5ff8acb66f99",
        "current_return": 0.0,
        "mc_prob": 59.24
    },
    "yUkgb3lY2i49L3EPbOaE": {
        "high_water_mark": 0.0,
        "armed": false,
        "name": "Copy of Feaver Dreams and NOVA | UVXY | Jope IRA",
        "account": "585b26c6-62bf-4a48-ab01-5ff8acb66f99",
        "current_return": 0.0,
        "mc_prob": 54.86
    },
    "wGw2rBls96wmOfC2ti14": {
        "high_water_mark": 0.0,
        "armed": false,
        "name": "Copy of DIA/FXI/QQQ FR | Europe, Gold, USA, Shorty mashup | okhi2u | Jope IRA",
        "account": "585b26c6-62bf-4a48-ab01-5ff8acb66f99",
        "current_return": 0.0,
        "mc_prob": 57.220000000000006
    },
    "o400LJjtPBsZZkI5Au3i": {
        "high_water_mark": 0.0,
        "armed": false,
        "name": "Copy of TWF STFU, HODL, and Chill | Jope IRA",
        "account": "585b26c6-62bf-4a48-ab01-5ff8acb66f99",
        "current_return": 0.0,
        "mc_prob": 61.6
    },
    "xPWHWFN6J0FL8ngRp1yk": {
        "high_water_mark": 0.0,
        "armed": false,
        "name": "Copy of US Equities Multi-Runner | DIA/FXI/QQQ FR | 2025-10-20 (VIXY -> UVIX) | Jope IRA",
        "account": "cf8b4d86-700e-4ba5-af5d-b4f0f53df041",
        "current_return": 0.0,
        "mc_prob": 52.44
    },
    "eM1gyeoCYbwaDEf2R9u2": {
        "high_water_mark": 0.0,
        "armed": false,
        "name": "Copy of Moon Mission v3 | Nova Fever FR | Jope IRA",
        "account": "cf8b4d86-700e-4ba5-af5d-b4f0f53df041",
        "current_return": 0.0,
        "mc_prob": 40.36
    },
    "jchsP1xhF0FxX9KSH5F8": {
        "high_water_mark": 0.0,
        "armed": false,
        "name": "Copy of Chocolatey Mini Benetton | 80% | Calmar",
        "account": "cf8b4d86-700e-4ba5-af5d-b4f0f53df041",
        "current_return": 0.0,
        "mc_prob": 55.1
    },
    "TzVXpFHMtZDroJek0uSP": {
        "high_water_mark": 0.0,
        "armed": false,
        "name": "Copy of HODL Chicken & Fried Rice | De-Debased Simplified Portfolio | Mini Benetton | 80% | Calmar | Jope IRA",
        "account": "cf8b4d86-700e-4ba5-af5d-b4f0f53df041",
        "current_return": 0.0,
        "mc_prob": 57.86
    },
    "nAzotRRalGAMRP4aqhCP": {
        "high_water_mark": 0.0,
        "armed": false,
        "name": "Copy of Nova Feaver FR | 2/3 Core | Jope IRA",
        "account": "cf8b4d86-700e-4ba5-af5d-b4f0f53df041",
        "current_return": 0.0,
        "mc_prob": 59.38
    },
    "cjyYToUmsUvhDLZDv2t9": {
        "high_water_mark": 0.0,
        "armed": false,
        "name": "Copy of Four square shorting homies | okhi2u | Mini Benetton | 80% | Calmar | Jope IRA",
        "account": "cf8b4d86-700e-4ba5-af5d-b4f0f53df041",
        "current_return": 0.0,
        "mc_prob": 56.00000000000001
    },
    "iynbFkpINVAJAz8dZOVF": {
        "high_water_mark": 0.0,
        "armed": false,
        "name": "Copy of 30y OS TQQQ | Mini AutoRunners VibeCheck or Chocolate Milk OPT | Mini Benetton | 80% | Calmar | Jope IRA",
        "account": "cf8b4d86-700e-4ba5-af5d-b4f0f53df041",
        "current_return": 0.0,
        "mc_prob": 59.5
    },
    "lrfzX7YEjMwJ6Om8zyoV": {
        "high_water_mark": 0.0,
        "armed": false,
        "name": "Copy of Long/Short Mini Benetton | 80% | Calmar | Jope IRA",
        "account": "cf8b4d86-700e-4ba5-af5d-b4f0f53df041",
        "current_return": 0.0,
        "mc_prob": 63.12
    },
    "bBw4EQQtfu6iK9EXvUsv": {
        "high_water_mark": 0.0,
        "armed": false,
        "name": "Copy of v3 The Absolute Lowest Vol High AR | Mini Benetton | 80% | Calmar | Jope IRA",
        "account": "cf8b4d86-700e-4ba5-af5d-b4f0f53df041",
        "current_return": 0.0,
        "mc_prob": 59.019999999999996
    },
    "0Dvuqqm3T8BvIgVlaj9j": {
        "high_water_mark": 0.0,
        "armed": false,
        "name": "Copy of 30y OS TQQQ | Nova Feaver 2/3 Core | Mini Benetton | 80% | Calmar | Jope IRA",
        "account": "cf8b4d86-700e-4ba5-af5d-b4f0f53df041",
        "current_return": 0.0,
        "mc_prob": 53.959999999999994
    },
    "rdpPQfA671QF4w9Rovps": {
        "high_water_mark": 0.0,
        "armed": false,
        "name": "Copy of Nova Feaver | Mini Benetton | 80% | Calmar | Jope IRA",
        "account": "cf8b4d86-700e-4ba5-af5d-b4f0f53df041",
        "current_return": 0.0,
        "mc_prob": 54.22
    },
    "QMPF774YUYHyhkQ0Bbba": {
        "high_water_mark": 0.0,
        "armed": false,
        "name": "Copy of Autotune OPTIMIZED Mix 2 Mini Benetton | 80% | Calmar | Jope IRA",
        "account": "cf8b4d86-700e-4ba5-af5d-b4f0f53df041",
        "current_return": 0.0,
        "mc_prob": 58.440000000000005
    },
    "TSe9VuxNVKhHIG5zy0i7": {
        "high_water_mark": 0.0,
        "armed": false,
        "name": "Copy of Feaver Dreams and NOVA | UVXY | Jope IRA",
        "account": "cf8b4d86-700e-4ba5-af5d-b4f0f53df041",
        "current_return": 0.0,
        "mc_prob": 55.879999999999995
    },
    "zQudngBiwLHYixD4edpK": {
        "high_water_mark": 0.0,
        "armed": false,
        "name": "Copy of Mini AutoRunners VibeCheck or Chocolate Milk OPT | Mini Benetton | 80% | Calmar | Jope IRA",
        "account": "cf8b4d86-700e-4ba5-af5d-b4f0f53df041",
        "current_return": 0.0,
        "mc_prob": 29.94
    },
    "h6nkpAAZV2WayPp8rZet": {
        "high_water_mark": 0.0,
        "armed": false,
        "name": "Copy of MOST AR NO MATTER WHAT STFU SIT DOWN AND HOLD ON v1.1 | Mini Benetton | 80% | Calmar | Jope IRA",
        "account": "cf8b4d86-700e-4ba5-af5d-b4f0f53df041",
        "current_return": 0.0,
        "mc_prob": 44.6
    },
    "pJQQzSb0Hm7yGenqZFAs": {
        "high_water_mark": 0.0,
        "armed": false,
        "name": "Copy of Golden Ratio Portfolio v20260210 (Zaied + Gold Nova Feaver + GOLD / UGL mixer + Nova Feaver) | Jope IRA",
        "account": "cf8b4d86-700e-4ba5-af5d-b4f0f53df041",
        "current_return": 0.0,
        "mc_prob": 56.99999999999999
    },
    "Vx9NWeVji2gXYMXqQcRR": {
        "high_water_mark": 0.0,
        "armed": false,
        "name": "Copy of DIA 1998 MA | Feaver Dream\u2122 | Jope IRA",
        "account": "cf8b4d86-700e-4ba5-af5d-b4f0f53df041",
        "current_return": 0.0,
        "mc_prob": 50.62
    },
    "0ATHYezOKnWDXJZt2uVn": {
        "high_water_mark": 0.0,
        "armed": false,
        "name": "Copy of v2 USD Nested SOXL Autotuned w/ a Shorty | Mini Benetton | 80% | Calmar | Jope IRA",
        "account": "cf8b4d86-700e-4ba5-af5d-b4f0f53df041",
        "current_return": 0.0,
        "mc_prob": 42.92
    },
    "V8yEk7jpMAzPy6Pm15Cb": {
        "high_water_mark": 0.0,
        "armed": false,
        "name": "Copy of TWF STFU, HODL, and Chill | Jope IRA",
        "account": "cf8b4d86-700e-4ba5-af5d-b4f0f53df041",
        "current_return": 0.0,
        "mc_prob": 61.8
    },
    "YpYU9tbn2KjBhKpDEb0w": {
        "high_water_mark": 0.0,
        "armed": false,
        "name": "Copy of QQQ 1996 MA | Feaver Dream\u2122 | Jope IRA",
        "account": "cf8b4d86-700e-4ba5-af5d-b4f0f53df041",
        "current_return": 0.0,
        "mc_prob": 60.9
    },
    "qJDX0gZLYhJCFFguxsnU": {
        "high_water_mark": 0.0,
        "armed": false,
        "name": "Copy of DIA/FXI/QQQ FR | Europe, Gold, USA, Shorty mashup | okhi2u | Jope IRA",
        "account": "cf8b4d86-700e-4ba5-af5d-b4f0f53df041",
        "current_return": 0.0,
        "mc_prob": 57.49999999999999
    },
    "gBMuafmih01jvpzcl81u": {
        "high_water_mark": 0.0,
        "armed": false,
        "name": "Copy of QQQ 1996 KMLM | Feaver Dream\u2122 | Jope IRA",
        "account": "cf8b4d86-700e-4ba5-af5d-b4f0f53df041",
        "current_return": 0.0,
        "mc_prob": 61.339999999999996
    },
    "0yyRSgm68NMIgZ18sZjC": {
        "high_water_mark": 0.0,
        "armed": false,
        "name": "Copy of DIA 1998 KMLM | Feaver Dream\u2122 | Jope IRA",
        "account": "cf8b4d86-700e-4ba5-af5d-b4f0f53df041",
        "current_return": 0.0,
        "mc_prob": 53.22
    }
}